notion_kit/CONTENTS.py
notion_kit/__init__.py
notion_kit/api.py
notion_kit/dict_gadget.py
notion_kit/gadget.py
notion_kit/object.py
notion_kit/tool.py
notion_kit_flexible-0.2.1.dist-info/LICENSE
notion_kit_flexible-0.2.1.dist-info/WHEEL
notion_kit_flexible-0.2.1.dist-info/METADATA
notion_kit_flexible-0.2.1.dist-info/RECORD
