Metadata-Version: 2.1
Name: notion-kit-flexible
Version: 0.2.1
Summary: Notion Kit but with some changes for even more convinence.
License: MIT
Author: Kevin Hill
Author-email: kivo360@gmail.com
Requires-Python: >=3.9,<4.0
Classifier: License :: OSI Approved :: MIT License
Classifier: Programming Language :: Python :: 3
Classifier: Programming Language :: Python :: 3.9
Classifier: Programming Language :: Python :: 3.10
Classifier: Programming Language :: Python :: 3.11
Requires-Dist: notion-client (>=2.0.0)
Requires-Dist: pydantic (>=1.10.9,<2.0.0)
Requires-Dist: pytz (>=2023.3,<2024.0)
